pysignalbot/__init__.py
pysignalbot/bot.py
pysignalbot/dispatcher.py
pysignalbot/exceptions.py
pysignalbot/filters.py
pysignalbot/handlers.py
pysignalbot/models.py
python_signal_bot-0.1.8.dist-info/licenses/LICENSE
python_signal_bot-0.1.8.dist-info/METADATA
python_signal_bot-0.1.8.dist-info/WHEEL
python_signal_bot-0.1.8.dist-info/top_level.txt
python_signal_bot-0.1.8.dist-info/RECORD
