Metadata-Version: 2.4
Name: python-signal-bot
Version: 0.1.8
Summary: Framework to easily write bots for messenger Signal
Author: 0x4c47
Project-URL: Homepage, https://gitlab.com/0x4c47/python-signal-bot
Project-URL: Bug Tracker, https://gitlab.com/0x4c47/python-signal-bot/-/issues
Classifier: Programming Language :: Python :: 3
Classifier: License :: OSI Approved :: GNU General Public License v3 (GPLv3)
Classifier: Operating System :: OS Independent
Requires-Python: >=3.6
License-File: LICENSE
Requires-Dist: async-timeout~=4.0.2
Dynamic: license-file
